iops/__init__.py
iops/main.py
iops-0.5.1.dist-info/LICENSE
iops-0.5.1.dist-info/METADATA
iops-0.5.1.dist-info/WHEEL
iops-0.5.1.dist-info/top_level.txt
iops-0.5.1.dist-info/RECORD
