Metadata-Version: 2.1
Name: iops
Version: 0.5.1
Summary: Open-source Python release of the IO-PS package
Home-page: https://github.com/WoutersResearchGroup/py-IO-PS
Author: Michael du Plessis and Martenique Swanepoel
Author-email: 20841175@sun.ac.za
Classifier: Programming Language :: Python :: 3
Classifier: License :: OSI Approved :: MIT License
Classifier: Operating System :: OS Independent
Requires-Python: >=3.6
License-File: LICENSE
